medley/__init__.py
medley/container.py
medley/errors.py
medley/service_provider.py
medley-1.0.4.dist-info/LICENSE
medley-1.0.4.dist-info/METADATA
medley-1.0.4.dist-info/WHEEL
medley-1.0.4.dist-info/top_level.txt
medley-1.0.4.dist-info/RECORD
