Metadata-Version: 2.1
Name: medley
Version: 1.0.4
Summary: A simple, lightweight Python Dependency Injection Container (IOC), inspired by Pimple
Home-page: https://github.com/illumineinteractive/medley
Author: Garret Bolthouse
Author-email: garret@illumineinteractive.com
License: UNKNOWN
Platform: UNKNOWN
Classifier: Development Status :: 5 - Production/Stable
Classifier: Intended Audience :: Developers
Classifier: Programming Language :: Python :: 2.7
Classifier: Programming Language :: Python :: 3.2
Classifier: Programming Language :: Python :: 3.3
Classifier: Programming Language :: Python :: 3.4
Classifier: Programming Language :: Python :: 3.5
Classifier: Programming Language :: Python :: 3.6
Classifier: Programming Language :: Python :: 3.7
Classifier: License :: OSI Approved :: MIT License
Classifier: Operating System :: OS Independent
Classifier: Topic :: Software Development :: Libraries :: Python Modules
Requires-Python: >=2.7
Requires-Dist: six
